{
    "ARC_AREA": 0,
    "ARC_BAR": 1,
    "ARC_LINE": 2,
    "ARC_POINT": 3,
    "ARC_RECT": 4,
    "AREA_BAR": 5,
    "AREA_LINE": 6,
    "AREA_POINT": 7,
    "AREA_RECT": 8,
    "BAR_LINE": 9,
    "BAR_POINT": 10,
    "BAR_RECT": 11,
    "LINE_POINT": 12,
    "LINE_RECT": 13,
    "POINT_RECT": 14,
    "SCALE": 15,
    "SORT": 16,
    "BIN": 17,
    "STACK_ZERO": 18,
    "STACK_NORMALIZE": 19,
    "AGGREGATE_COUNT": 20,
    "AGGREGATE_SUM": 21,
    "AGGREGATE_MEAN": 22,
    "LOESS": 23,
    "REGRESSION": 24,
    "ADD_FILTER": 25,
    "REMOVE_FILTER": 26,
    "MODIFY_FILTER": 27,
    "ADD_X": 28,
    "ADD_THETA": 29,
    "ADD_LONGITUDE": 30,
    "ADD_LATITUDE": 31,
    "ADD_Y": 32,
    "ADD_COLOR": 33,
    "ADD_SHAPE": 34,
    "ADD_SIZE": 35,
    "ADD_ROW": 36,
    "ADD_COLUMN": 37,
    "ADD_TEXT": 38,
    "ADD_X_COUNT": 39,
    "ADD_Y_COUNT": 40,
    "ADD_COLOR_COUNT": 41,
    "ADD_SHAPE_COUNT": 42,
    "ADD_SIZE_COUNT": 43,
    "ADD_ROW_COUNT": 44,
    "ADD_COLUMN_COUNT": 45,
    "ADD_TEXT_COUNT": 46,
    "REMOVE_X_COUNT": 47,
    "REMOVE_Y_COUNT": 48,
    "REMOVE_COLOR_COUNT": 49,
    "REMOVE_SHAPE_COUNT": 50,
    "REMOVE_SIZE_COUNT": 51,
    "REMOVE_ROW_COUNT": 52,
    "REMOVE_COLUMN_COUNT": 53,
    "REMOVE_TEXT_COUNT": 54,
    "REMOVE_X": 55,
    "REMOVE_THETA": 56,
    "REMOVE_LONGITUDE": 57,
    "REMOVE_LATITUDE": 58,
    "REMOVE_Y": 59,
    "REMOVE_COLOR": 60,
    "REMOVE_SHAPE": 61,
    "REMOVE_SIZE": 62,
    "REMOVE_ROW": 63,
    "REMOVE_COLUMN": 64,
    "REMOVE_TEXT": 65,
    "MODIFY_X": 66,
    "MODIFY_Y": 67,
    "MODIFY_COLOR": 68,
    "MODIFY_SHAPE": 69,
    "MODIFY_SIZE": 70,
    "MODIFY_ROW": 71,
    "MODIFY_COLUMN": 72,
    "MODIFY_TEXT": 73,
    "MODIFY_X_ADD_COUNT": 74,
    "MODIFY_Y_ADD_COUNT": 75,
    "MODIFY_COLOR_ADD_COUNT": 76,
    "MODIFY_SHAPE_ADD_COUNT": 77,
    "MODIFY_SIZE_ADD_COUNT": 78,
    "MODIFY_ROW_ADD_COUNT": 79,
    "MODIFY_COLUMN_ADD_COUNT": 80,
    "MODIFY_TEXT_ADD_COUNT": 81,
    "MODIFY_X_REMOVE_COUNT": 82,
    "MODIFY_Y_REMOVE_COUNT": 83,
    "MODIFY_COLOR_REMOVE_COUNT": 84,
    "MODIFY_SHAPE_REMOVE_COUNT": 85,
    "MODIFY_SIZE_REMOVE_COUNT": 86,
    "MODIFY_ROW_REMOVE_COUNT": 87,
    "MODIFY_COLUMN_REMOVE_COUNT": 88,
    "MODIFY_TEXT_REMOVE_COUNT": 89,
    "MOVE_X_ROW": 90,
    "MOVE_X_COLUMN": 91,
    "MOVE_X_SIZE": 92,
    "MOVE_X_SHAPE": 93,
    "MOVE_X_COLOR": 94,
    "MOVE_X_Y": 95,
    "MOVE_X_TEXT": 96,
    "MOVE_Y_ROW": 97,
    "MOVE_Y_COLUMN": 98,
    "MOVE_Y_SIZE": 99,
    "MOVE_Y_SHAPE": 100,
    "MOVE_Y_COLOR": 101,
    "MOVE_Y_X": 102,
    "MOVE_Y_TEXT": 103,
    "MOVE_COLOR_ROW": 104,
    "MOVE_COLOR_COLUMN": 105,
    "MOVE_COLOR_SIZE": 106,
    "MOVE_COLOR_SHAPE": 107,
    "MOVE_COLOR_Y": 108,
    "MOVE_COLOR_X": 109,
    "MOVE_COLOR_TEXT": 110,
    "MOVE_SHAPE_ROW": 111,
    "MOVE_SHAPE_COLUMN": 112,
    "MOVE_SHAPE_SIZE": 113,
    "MOVE_SHAPE_COLOR": 114,
    "MOVE_SHAPE_Y": 115,
    "MOVE_SHAPE_X": 116,
    "MOVE_SHAPE_TEXT": 117,
    "MOVE_SIZE_ROW": 118,
    "MOVE_SIZE_COLUMN": 119,
    "MOVE_SIZE_SHAPE": 120,
    "MOVE_SIZE_COLOR": 121,
    "MOVE_SIZE_Y": 122,
    "MOVE_SIZE_X": 123,
    "MOVE_SIZE_TEXT": 124,
    "MOVE_TEXT_ROW": 125,
    "MOVE_TEXT_COLUMN": 126,
    "MOVE_TEXT_SHAPE": 127,
    "MOVE_TEXT_COLOR": 128,
    "MOVE_TEXT_Y": 129,
    "MOVE_TEXT_X": 130,
    "MOVE_TEXT_SIZE": 131,
    "MOVE_COLUMN_ROW": 132,
    "MOVE_COLUMN_SIZE": 133,
    "MOVE_COLUMN_SHAPE": 134,
    "MOVE_COLUMN_COLOR": 135,
    "MOVE_COLUMN_Y": 136,
    "MOVE_COLUMN_X": 137,
    "MOVE_COLUMN_TEXT": 138,
    "MOVE_ROW_COLUMN": 139,
    "MOVE_ROW_SIZE": 140,
    "MOVE_ROW_SHAPE": 141,
    "MOVE_ROW_COLOR": 142,
    "MOVE_ROW_Y": 143,
    "MOVE_ROW_X": 144,
    "MOVE_ROW_TEXT": 145,
    "SWAP_X_Y": 146,
    "SWAP_ROW_COLUMN": 147,
    "retrieve_value__rect": 148,
    "filter__rect": 149,
    "filter__bar": 150,
    "filter__arc": 151,
    "compute_derived_value__rect": 152,
    "compute_derived_value__arc": 153,
    "compute_derived_value__bar": 154,
    "find_extremum__bar": 155,
    "find_extremum__point": 156,
    "sort__bar": 157,
    "determine_range__boxplot": 158,
    "determine_range__tick": 159,
    "characterize_distribution__bar": 160,
    "characterize_distribution__point": 161,
    "find_anomalies__bar": 162,
    "find_anomalies__point": 163,
    "cluster__bar": 164,
    "cluster__point": 165,
    "correlate__bar": 166,
    "correlate__line": 167,
    "part_to_whole__arc": 168,
    "change_over_time__line": 169,
    "change_over_time__area": 170,
    "magnitude__arc": 171,
    "magnitude__bar": 172,
    "comparison__line": 173,
    "comparison__point": 174,
    "comparison__bar": 175,
    "spatial__circle": 176,
    "deviation__bar": 177,
    "deviation__area": 178,
    "trend__point": 179,
    "error_range__errorbar": 180,
    "error_range__errorband": 181
}